{
  "menu": [
    {
      "id": 1,
      "title": "Home",
      "ruTitle": "Главная"
    },
    {
      "id": 2,
      "title": "Repairs",
      "ruTitle": "Ремонт"
    },
    {
      "id": 3,
      "title": "Design",
      "ruTitle": "Дизайн"
    },
    {
      "id": 4,
      "title": "About",
      "ruTitle": "О компании"
    },
    {
      "id": 5,
      "title": "Contacts",
      "ruTitle": "Контакты"
    }
  ],
  "button": [
    {
      "id": 1,
      "buttonHeader": "Оставить заявку",
      "shortTitle": "leave_request"
    },
    {
      "id": 2,
      "buttonHeader": "Заказать проект",
      "shortTitle": "order_project"
    },
    {
      "id": 3,
      "buttonHeader": "Получить консультацию",
      "shortTitle": "get_counseling"
    }
  ],
  "panel": [
    {
      "id": "phoneButton",
      "icon": "/panel/phone.svg",
      "altText": "Телефон",
      "text": "Получить консультацию",
      "position": {
        "bottom": "61%"
      }
    },
    {
      "id": "calculatorButton",
      "icon": "/panel/calculator.svg",
      "altText": "Калькулятор",
      "text": "Рассчитать стоимость",
      "position": {
        "bottom": "49%"
      }
    },
    {
      "id": "chatButton",
      "icon": "/panel/chat.svg",
      "altText": "Чат",
      "text": "Спросить в чате",
      "position": {
        "bottom": "55%"
      }
    }
  ],
  "news": [
    {
      "id": 1,
      "image": "/news/news01.webp",
      "imagePng": "/news/news01.png",
      "title": "Летние скидки на ремонт и дизайн интерьеров - ограниченное предложение!",
      "text": "Успейте воспользоваться нашей летней акцией и получите скидку до 20% на ремонт и дизайн вашего интерьера. Создайте уют и стиль в своем доме по выгодной цене. Заполните форму заявки прямо сейчас!",
      "date": "15.05.2023 - 15.06.2023"
    },
    {
      "id": 2,
      "image": "/news/news02.webp",
      "imagePng": "/news/news02.png",
      "title": "Дизайн интерьера под ключ со скидкой - ограниченное предложение!",
      "text": "Хотите полностью обновить свой интерьер? Закажите у нас дизайн под ключ и получите скидку 15%. Мы разработаем уникальный дизайн, проведем ремонт и подберем мебель - все, что вам нужно для создания идеального пространства.",
      "date": "26.05.2023 - 26.11.2023"
    },
    {
      "id": 3,
      "image": "/news/news03.webp",
      "imagePng": "/news/news03.png",
      "title": "Бесплатная доставка материала при заказе ремонта и дизайна интерьера!",
      "text": "Ремонт и дизайн интерьера не только преображают ваш дом, но и требуют затрат. Мы поможем вам сэкономить на доставке материала - она будет бесплатной при заказе комплексного обслуживания. Заявка на сайте займет всего несколько минут!",
      "date": "01.09.2023 - 24.12.2023"
    },
    {
      "id": 4,
      "image": "/news/news04.webp",
      "imagePng": "/news/news04.png",
      "title": "Раскрасьте свой дом - скидка на покраску стен!",
      "text": "Хотите освежить свой интерьер? Закажите у нас покраску стен и получите скидку 10%. Мы используем только качественные материалы и предлагаем широкую палитру цветов. Позвоните нам или оставьте заявку на сайте!",
      "date": "01.09.2023 - 24.12.2023"
    },
    {
      "id": 5,
      "image": "/news/news05.webp",
      "imagePng": "/news/news05.png",
      "title": "Уютное гнездышко для вашего ребенка - детская комната со скидкой!",
      "text": "Хотите создать магическую атмосферу в комнате вашего ребенка? Закажите дизайн и ремонт детской комнаты у нас и получите скидку 10%. Мы сделаем комнату функциональной, безопасной и вдохновляющей для вашего малыша.",
      "date": "01.09.2023 - 24.12.2023"
    },
    {
      "id": 6,
      "image": "/news/news06.webp",
      "imagePng": "/news/news06.png",
      "title": "Превратите свою кухню в кулинарное кино - скидка на дизайн и ремонт кухни!",
      "text": "Кухня - это место, где рождаются шедевры. Сделайте свою кухню стильной и функциональной с помощью наших услуг. Закажите дизайн и ремонт кухни у нас и получите скидку 15%. Позвольте своей кулинарной фантазии развернуться!",
      "date": "01.09.2023 - 24.12.2023"
    }
  ],
  "features": [
    {
      "id": 1,
      "title": "Оптимальные сроки",
      "iconPng": "/features/clock.png",
      "icon": "/features/clock.webp"
    },
    {
      "id": 2,
      "title": "Разумные цены",
      "iconPng": "/features/economy.png",
      "icon": "/features/economy.webp"
    },
    {
      "id": 3,
      "title": "Ответственные мастера",
      "iconPng": "/features/leader.png",
      "icon": "/features/leader.webp"
    },
    {
      "id": 4,
      "title": "Гарантия 2 года",
      "iconPng": "/features/shield.png",
      "icon": "/features/shield.webp"
    }
  ],
  "title": [
    {
      "id": 1,
      "title": "Ремонт и Дизайн интерьеров в Беларуси",
      "shortTitle": "repair-and-design",
      "description": "Уникальные авторские и индивидуальные дизайны, проектируем и делаем ремонт под ключ."
    },
    {
      "id": 2,
      "title": "Трансформация вашего пространства — от идеи до реализации",
      "shortTitle": "services",
      "description": "Доверьтесь профессионалам — мы гарантируем результат, который превзойдет ваши ожидания."
    },
    {
      "id": 3,
      "title": "Наш подход",
      "shortTitle": "our-approach",
      "description": "Придерживаемся индивидуального подхода ко всем нашим клиентам. Помогаем в разрешении любых возникающих сложностей и трудностей."
    },
    {
      "id": 4,
      "title": "Примеры наших работ",
      "shortTitle": "our-works",
      "description": "Мы предлагаем не просто дизайн, а возможность воплотить ваши самые смелые идеи в реальность. Будь то стильная современность или вечная классика — мы поможем создать интерьер, который подчеркнет вашу индивидуальность и вкус. Наши работы — это не только пространство, но и отражение вашей личности."
    },
    {
      "id": 5,
      "title": "Калькулятор расчёта стоимости 'под ключ'",
      "shortTitle": "price-calculation",
      "description": "Получите точную оценку стоимости вашего проекта, выбрав подходящую услугу. Укажите площадь и тип помещения, и мы рассчитаем стоимость, исходя из ваших пожеланий. Это быстрый и удобный способ сориентироваться в цене наших решений для вашего дома или бизнеса."
    },
    {
      "id": 6,
      "title": "Создайте лучшее место для жизни",
      "shortTitle": "create-best-place",
      "description": "Оставьте заявку сегодня, и новоселье станет на один шаг ближе."
    },
    {
      "id": 7,
      "title": "Мечты о комфорте станут реальностью",
      "shortTitle": "comfort-dreams",
      "description": "Разработка дизайн-проекта — это первый шаг на пути к созданию стильного, функционального, современного помещения."
    },
    {
      "id": 8,
      "title": "Premium Interior | Ремонт и дизайн интерьеров в Беларуси",
      "shortTitle": "premium-interior",
      "description": "Уникальные авторские и индивидуальные дизайны, проектируем и делаем ремонт под ключ."
    },
    {
      "id": 9,
      "title": "Ремонт может быть приятным",
      "shortTitle": "pleasant-repair",
      "description": "Решаем самые сложные задачи, проектируем и делаем ремонт под ключ."
    },
    {
      "id": 10,
      "title": "Узнайте больше о наших ценностях!",
      "shortTitle": "our-values",
      "description": "Компания с многолетним опытом работы и профессиональной командой специалистов."
    },
    {
      "id": 11,
      "title": "Мы всегда рады помочь вам!",
      "shortTitle": "we-are-here-to-help",
      "description": "Свяжитесь с нами, чтобы обсудить свои идеи и сделать ваше пространство уютным и современным."
    },
    {
      "id": 12,
      "title": "Получите скидки на строительные материалы!",
      "shortTitle": "our-partners",
      "description": "Мы сотрудничаем с ведущими компаниями, предлагающими высококачественные товары и услуги, чтобы удовлетворить все ваши потребности. Это позволит вам сэкономить бюджет, сохранив высокое качество работ."
    },
    {
      "id": 13,
      "title": "Этапы рассмотрения заявок",
      "shortTitle": "application-process",
      "description": "Процесс, который приведет Вас к успеху: от начала до финиша."
    },
    {
      "id": 14,
      "title": "Актуальные услуги и цены",
      "shortTitle": "repair-categories",
      "description": "Подберите интересующую вас услугу и свяжитесь с нами."
    },
    {
      "id": 15,
      "title": "Отзывы наших клиентов",
      "shortTitle": "customer_reviews",
      "description": "Мы гордимся доверием наших клиентов и всегда стремимся к совершенству. Вот что говорят о нас те, кто уже воспользовался нашими услугами.."
    },
    {
      "id": 16,
      "title": "Все для вашего удобства и спокойствия",
      "shortTitle": "related-services",
      "description": "Мы знаем, что для создания идеального пространства важны не только ремонтные работы, но и дополнительные детали. Мы предлагаем уникальные решения, которые облегчают вашу жизнь: от умного дома до энергоэффективных технологий."
    }
  ],
  "bannersImages": [
    {
      "id": 1,
      "src": "/banners/banner-home.webp",
      "alt": "Premium Interior - Ремонт и дизайн интерьеров в Беларуси",
      "quality": 95,
      "width": 1935,
      "height": 684,
      "shortTitle": "home_banner"
    },
    {
      "id": 2,
      "src": "/banners/banner-repair.webp",
      "alt": "Premium Interior - Ремонт и дизайн интерьеров в Беларуси",
      "quality": 95,
      "width": 1935,
      "height": 684,
      "shortTitle": "repair_banner"
    },
    {
      "id": 3,
      "src": "/banners/banner-design.webp",
      "alt": "Premium Interior - Ремонт и дизайн интерьеров в Беларуси",
      "quality": 95,
      "width": 1935,
      "height": 684,
      "shortTitle": "design_banner"
    },
    {
      "id": 4,
      "src": "/banners/banner-about.webp",
      "alt": "Premium Interior - Ремонт и дизайн интерьеров в Беларуси",
      "quality": 95,
      "width": 1935,
      "height": 684,
      "shortTitle": "about_banner"
    },
    {
      "id": 5,
      "src": "/banners/banner-contacts.webp",
      "alt": "Premium Interior - Ремонт и дизайн интерьеров в Беларуси",
      "quality": 95,
      "width": 1935,
      "height": 684,
      "shortTitle": "contacts_banner"
    },
    {
      "id": 6,
      "src": "/banners/appeal.webp",
      "alt": "Premium Interior - Ремонт и дизайн интерьеров в Беларуси",
      "quality": 95,
      "width": 1935,
      "height": 684,
      "shortTitle": "appeal_banner"
    }
  ],
  "partners": [
    {
      "id": 1,
      "src": "/partners/marketBuild.webp",
      "srcPng": "/partners/marketBuild.png",
      "alt": "Premium Interior - Ремонт и дизайн интерьеров в Беларуси",
      "quality": 95,
      "width": 320,
      "height": 140,
      "discounts": "Скидка до 8%"
    },
    {
      "id": 2,
      "src": "/partners/shopOMA.webp",
      "srcPng": "/partners/shopOMA.png",
      "alt": "Premium Interior - Ремонт и дизайн интерьеров в Беларуси",
      "quality": 95,
      "width": 320,
      "height": 140,
      "discounts": "Скидка до 7%"
    },
    {
      "id": 3,
      "src": "/partners/MarketKSK.webp",
      "srcPng": "/partners/MarketKSK.png",
      "alt": "Premium Interior - Ремонт и дизайн интерьеров в Беларуси",
      "quality": 95,
      "width": 320,
      "height": 140,
      "discounts": "Скидка до 7%"
    },
    {
      "id": 4,
      "src": "/partners/electricsVolt.webp",
      "srcPng": "/partners/electricsVolt.png",
      "alt": "Premium Interior - Ремонт и дизайн интерьеров в Беларуси",
      "quality": 95,
      "width": 320,
      "height": 140,
      "discounts": "Скидка до 7%"
    },
    {
      "id": 5,
      "src": "/partners/parquetTarkett.webp",
      "srcPng": "/partners/parquetTarkett.png",
      "alt": "Premium Interior - Ремонт и дизайн интерьеров в Беларуси",
      "quality": 95,
      "width": 320,
      "height": 140,
      "discounts": "Скидка до 7%"
    },
    {
      "id": 6,
      "src": "/partners/doorsJurkas.webp",
      "srcPng": "/partners/doorsJurkas.png",
      "alt": "Premium Interior - Ремонт и дизайн интерьеров в Беларуси",
      "quality": 95,
      "width": 320,
      "height": 140,
      "discounts": "Скидка до 7%"
    },
    {
      "id": 7,
      "src": "/partners/plumbingAquarius.webp",
      "srcPng": "/partners/plumbingAquarius.png",
      "alt": "Premium Interior - Ремонт и дизайн интерьеров в Беларуси",
      "quality": 95,
      "width": 320,
      "height": 140,
      "discounts": "Скидка до 10%"
    },
    {
      "id": 8,
      "src": "/partners/fsHome.webp",
      "srcPng": "/partners/fsHome.png",
      "alt": "Premium Interior - Ремонт и дизайн интерьеров в Беларуси",
      "quality": 95,
      "width": 320,
      "height": 140,
      "discounts": "Скидка до 8%"
    }
  ],
  "cards": {
    "approachCard": [
      {
        "id": 1,
        "image": "/approach/approach01.svg",
        "title": "Выезд оценщика",
        "description": "Любые консультации и составление сметы – БЕСПЛАТНО"
      },
      {
        "id": 2,
        "image": "/approach/approach02.svg",
        "title": "Помощь с материалами",
        "description": "Помощь в выборе и закупке чистовых материалов – БЕСПЛАТНО!"
      },
      {
        "id": 3,
        "image": "/approach/approach03.svg",
        "title": "Дизайн-проект",
        "description": "Базовый дизайн-проект, экономит Вам до 25% стоимости - БЕСПЛАТНО."
      },
      {
        "id": 4,
        "image": "/approach/approach04.svg",
        "title": "Минимизация расходов",
        "description": "Качественный ремонт дешевле чем Вы думаете!"
      }
    ],
    "costingCard": [
      {
        "id": 1,
        "title": "Ремонт квартиры",
        "image": "/costing/costing01.webp"
      },
      {
        "id": 2,
        "title": "Ремонт дома",
        "image": "/costing/costing02.webp"
      },
      {
        "id": 3,
        "title": "Ремонт магазина",
        "image": "/costing/costing03.webp"
      },
      {
        "id": 4,
        "title": "Ремонт ресторана",
        "image": "/costing/costing04.webp"
      },
      {
        "id": 5,
        "title": "Ремонт офиса",
        "image": "/costing/costing05.webp"
      }
    ],
    "examplesCard": [
      {
        "id": 1,
        "background": "/examples/example01.webp",
        "address": "Ремонт квартиры. г.Жлобин",
        "deadlines": "Срок выполнения 5,5 мес.",
        "bathroomIcon": "/examples/bathroomIcon.svg",
        "bathroomOption": 1,
        "areaIcon": "/examples/areaIcon.svg",
        "areaOption": 49,
        "areaSquare": "m2",
        "images": [
          "/viewer/apartment/01.webp",
          "/viewer/apartment/02.webp",
          "/viewer/apartment/03.webp",
          "/viewer/apartment/04.webp",
          "/viewer/apartment/05.webp"
        ]
      },
      {
        "id": 2,
        "background": "/examples/example02.webp",
        "address": "Ремонт дома. д.Малые Роги",
        "deadlines": "Срок выполнения 1 мес.",
        "bathroomIcon": "/examples/bathroomIcon.svg",
        "bathroomOption": 1,
        "areaIcon": "/examples/areaIcon.svg",
        "areaOption": 80,
        "areaSquare": "m2",
        "images": [
          "/viewer/cottage/01.webp",
          "/viewer/cottage/02.webp",
          "/viewer/cottage/03.webp",
          "/viewer/cottage/04.webp",
          "/viewer/cottage/05.webp"
        ]
      },
      {
        "id": 3,
        "background": "/examples/example03.webp",
        "address": "Ремонт дома. п.Сейбит",
        "deadlines": "Срок выполнения 4 мес.",
        "bathroomIcon": "/examples/bathroomIcon.svg",
        "bathroomOption": 1,
        "areaIcon": "/examples/areaIcon.svg",
        "areaOption": 42,
        "areaSquare": "m2",
        "images": [
          "/viewer/home/01.webp",
          "/viewer/home/02.webp",
          "/viewer/home/03.webp",
          "/viewer/home/04.webp"
        ]
      },
      {
        "id": 4,
        "background": "/examples/example04.webp",
        "address": "Ремонт магазина IMPERIAL",
        "deadlines": "Срок выполнения 2 мес.",
        "bathroomIcon": "/examples/bathroomIcon.svg",
        "bathroomOption": 0,
        "areaIcon": "/examples/areaIcon.svg",
        "areaOption": 108,
        "areaSquare": "m2",
        "images": [
          "/viewer/imperial/01.webp",
          "/viewer/imperial/02.webp",
          "/viewer/imperial/03.webp"
        ]
      },
      {
        "id": 5,
        "background": "/examples/example05.webp",
        "address": "Ремонт павильона IQOS",
        "deadlines": "Срок выполнения 1,5 мес.",
        "bathroomIcon": "/examples/bathroomIcon.svg",
        "bathroomOption": 1,
        "areaIcon": "/examples/areaIcon.svg",
        "areaOption": 70,
        "areaSquare": "m2",
        "images": [
          "/viewer/iqos/01.webp",
          "/viewer/iqos/02.webp",
          "/viewer/iqos/03.webp",
          "/viewer/iqos/04.webp",
          "/viewer/iqos/05.webp"
        ]
      },
      {
        "id": 6,
        "background": "/examples/example06.webp",
        "address": "Ремонт ресторана Колбасный Цех",
        "deadlines": "Срок выполнения 2 мес.",
        "bathroomIcon": "/examples/bathroomIcon.svg",
        "bathroomOption": 2,
        "areaIcon": "/examples/areaIcon.svg",
        "areaOption": 150,
        "areaSquare": "m2",
        "images": [
          "/viewer/workshop/01.webp",
          "/viewer/workshop/02.webp",
          "/viewer/workshop/03.webp",
          "/viewer/workshop/04.webp",
          "/viewer/workshop/05.webp"
        ]
      }
    ],
    "servicesCard": [
      {
        "id": 1,
        "text": "Дизайн интерьеров",
        "image": "/services/service01.webp",
        "href": "/design"
      },
      {
        "id": 2,
        "text": "Ремонт интерьеров",
        "image": "/services/service02.webp",
        "href": "/repairs"
      },
      {
        "id": 3,
        "text": "Сопутствующие услуги",
        "image": "/services/service03.webp",
        "href": "/#related-services"
      },
      {
        "id": 4,
        "text": "Акции",
        "image": "/services/service05.webp",
        "href": "/about#news-1"
      },
      {
        "id": 5,
        "text": "Ремонт для бизнеса",
        "image": "/services/service04.webp",
        "href": "/repairs#repair-for-business"
      }
    ]
  },
  "offerList": {
    "homeType": {
      "id": 1,
      "image": "/design/offerList.webp",
      "title": "Воплощаем мечты в реальность: интерьер вашей мечты — без компромиссов!",
      "description": "Добро пожаловать в компанию, где ваши идеи превращаются в стильные и функциональные пространства! Мы объединяем дизайн, ремонт и инновации, чтобы создать дом, в который вы будете возвращаться с радостью каждый день.",
      "questions": [
        "Что делает ваш дом уютным и отражающим вашу индивидуальность?",
        "Почему профессиональный подход экономит время и средства?",
        "Какие детали делают ремонт или дизайн проект действительно выдающимся?",
        "Как мы гарантируем 100% результат и соблюдение сроков?",
        "Почему нас рекомендуют друзья и партнеры?"
      ],
      "tips": "Превратите вашу мечту в реальность! Ознакомьтесь с нашими проектами и начните трансформацию вашего пространства уже сегодня. Успех начинается с первого шага — сделайте его прямо сейчас!",
      "shortTitle": "design_offer"
    },
    "designType": {
      "id": 1,
      "image": "/repair/offerList.webp",
      "title": "Добро пожаловать в мир ремонта и дизайна, где ваши мечты об идеальном интерьере становятся реальностью!",
      "description": "Мы предлагаем комплексные решения для создания стильных и уютных интерьеров. Наши специалисты работают с вниманием к деталям, чтобы ваши идеи воплощались максимально точно и качественно.",
      "questions": [
        "Почему стоит доверить ремонт и дизайн профессионалам?",
        "Какие этапы включает наш подход к созданию идеального интерьера?",
        "Как мы помогаем экономить время и бюджет?",
        "Что делает наши проекты уникальными и современными?",
        "Где можно ознакомиться с готовыми проектами?"
      ],
      "tips": "Посетите наш каталог проектов, узнайте больше о наших услугах и свяжитесь с нами, чтобы сделать первый шаг к вашему идеальному интерьеру!",
      "shortTitle": "design_offer"
    },
    "repairType": {
      "id": 2,
      "image": "/repair/offerList.webp",
      "title": "Качественный ремонт под ключ — комфорт без лишних хлопот!",
      "description": "Наш комплексный ремонт — это полный цикл работ, начиная с оценки помещения и заканчивая расстановкой мебели. С нами вы получите идеальный результат точно в срок и по фиксированной стоимости.",
      "questions": [
        "Какие работы нужно выполнить для обновления интерьера?",
        "Как выбрать материалы, чтобы обеспечить долговечность и стиль?",
        "Какие технологии ускорят ремонт и сэкономят ваши средства?",
        "Как уложиться в сроки и бюджет?",
        "Почему мы гарантируем качество и надежность?"
      ],
      "tips": "Посмотрите наши работы, чтобы убедиться в качестве! Выберите вариант, который подходит именно вам, и мы воплотим его с максимальной точностью.",
      "shortTitle": "repairs_offer"
    },
    "aboutType": {
      "id": 3,
      "image": "/about/offerList.webp",
      "title": "Почему клиенты выбирают нас? Узнайте о наших преимуществах!",
      "description": "Ключевые преимущества нашей компании:\nМы — команда профессионалов с многолетним опытом в ремонте и дизайне интерьеров. Мы предлагаем:\n\nИндивидуальный подход к каждому проекту.\nИспользование современных технологий и материалов.\nПортфолио успешных проектов и восторженные отзывы клиентов.\nНаши работы — это сочетание эстетики, комфорта и функциональности. Мы создаем пространства, которые вдохновляют.",
      "questions": [
        "Чем наша компания отличается от конкурентов?",
        "Как мы гарантируем 100% качество и выполнение сроков?",
        "Какие выгоды получают наши клиенты?",
        "Почему нам доверяют сотни заказчиков?",
        "Где посмотреть примеры наших реализованных проектов?"
      ],
      "tips": "Загляните в наше портфолио и вдохновитесь идеями для вашего интерьера. Мы готовы создать пространство вашей мечты!",
      "shortTitle": "about_offer"
    }
  },
  "offerProject": {
    "designType": [
      {
        "id": 1,
        "image": "/design/designType1.webp",
        "title": "Стандарт",
        "price": "от 55 бел.руб. за 1 м. кв.",
        "pros": "Вы получаете:",
        "prosDescription": [
          "Выезд специалиста для замеров помещения",
          "Фотофиксация помещений",
          "План обмерный с точными размерами",
          "План расстановки мебели и оборудования (неограниченное кол-во)",
          "План демонтируемых перегородок",
          "План возведения новых перегородок",
          "План размещения сантехнических приборов",
          "План теплых полов и терморегуляторов",
          "План пола с указанием уровня и типа напольного покрытия",
          "План устройства потолков и потолочных карнизов",
          "План размещения светильников, световых групп и выключателей",
          "План размещения светильников, световых групп и выключателей",
          "План размещения электрических розеток",
          "План размещения дверей, дверных и оконных проемов",
          "Смета на предстоящие отделочные работы",
          "Создание альбома формата А3",
          "Электронная версия дизайн проекта"
        ],
        "cons": "В стоимость работ не входит:",
        "consDescription": [
          "Художественные коллажи каждого помещения (неограниченное кол-во)",
          "Фотореалистичная 3D визуализация (эскизы интерьера)",
          "Развертки санузлов с раскладкой плитки",
          "Развертки всех помещений по стенам",
          "Подбор отделочных материалов",
          "Подбор мебели с указанием артикула и производителя",
          "Подбор осветительных приборов и люстр",
          "Подборка и спецификация дверей",
          "Подборка бытовой техники и оборудования",
          "Чертежи декоративных заказных изделий",
          "Авторский надзор за реализацией проекта (1 выезд на объект в месяц)",
          "Декорирование интерьера (3 выезда)",
          "Авторский надзор(выезд 1 раз в неделю, внесение правок,контроль за выполнением проекта, поездки с заказчиком по магазинам материалов и мебели)на протяжении всего срока ремонта"
        ]
      },
      {
        "id": 2,
        "image": "/design/designType2.webp",
        "title": "Оптимальный",
        "price": "от 76 бел.руб. за 1 м. кв.",
        "pros": "Вы получаете:",
        "prosDescription": [
          "Выезд специалиста для замеров помещения",
          "Фотофиксация помещений",
          "План обмерный с точными размерами",
          "План расстановки мебели и оборудования (неограниченное кол-во)",
          "План демонтируемых перегородок",
          "План возведения новых перегородок",
          "План размещения сантехнических приборов",
          "План теплых полов и терморегуляторов",
          "План пола с указанием уровня и типа напольного покрытия",
          "План устройства потолков и потолочных карнизов",
          "План размещения светильников, световых групп и выключателей",
          "План размещения светильников, световых групп и выключателей",
          "План размещения электрических розеток",
          "План размещения дверей, дверных и оконных проемов",
          "Смета на предстоящие отделочные работы",
          "Создание альбома формата А3",
          "Электронная версия дизайн проекта",
          "Художественные коллажи каждого помещения (неограниченное кол-во)",
          "Фотореалистичная 3D визуализация (эскизы интерьера)",
          "Развертки санузлов с раскладкой плитки",
          "Развертки всех помещений по стенам",
          "Подбор отделочных материалов",
          "Подбор мебели с указанием артикула и производителя",
          "Подбор осветительных приборов и люстр",
          "Подборка и спецификация дверей"
        ],
        "cons": "В стоимость работ не входит:",
        "consDescription": [
          "Подборка бытовой техники и оборудования",
          "Чертежи декоративных заказных изделий",
          "Авторский надзор за реализацией проекта (1 выезд на объект в месяц)",
          "Декорирование интерьера (3 выезда)",
          "Авторский надзор(выезд 1 раз в неделю, внесение правок,контроль за выполнением проекта, поездки с заказчиком по магазинам материалов и мебели)на протяжении всего срока ремонта"
        ]
      },
      {
        "id": 3,
        "image": "/design/designType3.webp",
        "title": "Премиум",
        "price": "от 140 бел.руб. за 1 м. кв.",
        "pros": "Вы получаете:",
        "prosDescription": [
          "Выезд специалиста для замеров помещения",
          "Фотофиксация помещений",
          "План обмерный с точными размерами",
          "План расстановки мебели и оборудования (неограниченное кол-во)",
          "План демонтируемых перегородок",
          "План возведения новых перегородок",
          "План размещения сантехнических приборов",
          "План теплых полов и терморегуляторов",
          "План пола с указанием уровня и типа напольного покрытия",
          "План устройства потолков и потолочных карнизов",
          "План размещения светильников, световых групп и выключателей",
          "План размещения светильников, световых групп и выключателей",
          "План размещения электрических розеток",
          "План размещения дверей, дверных и оконных проемов",
          "Смета на предстоящие отделочные работы",
          "Создание альбома формата А3",
          "Электронная версия дизайн проекта",
          "Художественные коллажи каждого помещения (неограниченное кол-во)",
          "Фотореалистичная 3D визуализация (эскизы интерьера)",
          "Развертки санузлов с раскладкой плитки",
          "Развертки всех помещений по стенам",
          "Подбор отделочных материалов",
          "Подбор мебели с указанием артикула и производителя",
          "Подбор осветительных приборов и люстр",
          "Подборка и спецификация дверей",
          "Подборка бытовой техники и оборудования",
          "Чертежи декоративных заказных изделий",
          "Авторский надзор за реализацией проекта (1 выезд на объект в месяц)",
          "Декорирование интерьера (3 выезда)",
          "Авторский надзор(выезд 1 раз в неделю, внесение правок,контроль за выполнением проекта, поездки с заказчиком по магазинам материалов и мебели)на протяжении всего срока ремонта"
        ],
        "cons": "",
        "consDescription": []
      }
    ],
    "repairType": [
      {
        "id": 1,
        "image": "/repair/repairType1.webp",
        "title": "Стандарт",
        "price": "от 259 бел.руб. за 1 м. кв.",
        "pros": "Перечень работ включает:",
        "prosDescription": [
          "Демонтаж старых конструкций и элементов отделки",
          "Выравнивание пола, монтаж напольного покрытия",
          "Незначительная перепланировка без возведения внутренних перегородок",
          "Монтаж электропроводки, водопровода, канализации, сантехники",
          "Плиточные работы",
          "Выравнивание стен по маякам",
          "Шпатлевка, грунтовка поверхностей",
          "Установка ламината, линолеума, ковролина",
          "Оклейка обоев, покраска стен",
          "Монтаж натяжных потолков",
          "Монтаж отопления, умных инженерных систем, климатического оборудования, сантехники"
        ],
        "cons": "В стоимость работ не входит:",
        "consDescription": [
          "Дизайн проекта",
          "Замена дверей и окон",
          "Монтаж вентиляции, отопления и сложных инженерных сетей",
          "Применение экономичных стройматериалов и элементов отделки",
          "Выполняем стандартную отделку улучшенного качества, с применение экономичных стройматериалов и элементов отделки",
          "Сложные интерьерные декоры",
          "Создания гидро-, шумо- и теплоизоляции",
          "Используем только качественные отделочные материалы и доступные по цене технологии"
        ]
      },
      {
        "id": 2,
        "image": "/repair/repairType2.webp",
        "title": "Комфорт",
        "price": "от 369 бел.руб. за 1 м. кв.",
        "pros": "Перечень работ включает:",
        "prosDescription": [
          "Демонтаж старых конструкций и элементов отделки",
          "Монтаж электросетей, водопровода, канализации",
          "Монтаж отопления, умных инженерных систем, климатического оборудования, сантехники",
          "Выравнивание стен, пола, потолка, штукатурка, шпаклевка, грунтовка",
          "Создание гидро-, звуко- и теплоизоляции",
          "Покраска, оклейка обоев, плиточные работы",
          "Перепланировка помещений",
          "Монтаж напольных покрытий",
          "Установка гипсокартонных конструкций, натяжных потолков, окон, дверей, перегородок",
          "Декоративная отделка любой сложности"
        ],
        "cons": "Отличия от премиум и элит класса:",
        "consDescription": [
          "Разработка индивидуального дизайн-проекта",
          "Разумная экономия на декоре и отделочных материалах",
          "Менее сложные технические решения",
          "Неограниченный выбор стилистических решений",
          "Натуральные и синтетические материалы безупречного качества"
        ]
      },
      {
        "id": 3,
        "image": "/repair/repairType3.webp",
        "title": "Бизнес",
        "price": "от 554 бел.руб. за 1 м. кв.",
        "pros": "Перечень работ включает:",
        "prosDescription": [
          "Авторский дизайн-проект",
          "Любая стилистика на выбор",
          "Прогрессивные технологии",
          "Монтаж напольных покрытий",
          "Все виды модного декора",
          "Перепланировка помещений",
          "Демонтаж старых конструкций и элементов отделки",
          "Монтаж электросетей, водопровода, канализации",
          "Монтаж отопления, умных инженерных систем, климатического оборудования, сантехники",
          "Выравнивание стен, пола, потолка, штукатурка, шпаклевка, грунтовка",
          "Создание гидро-, звуко- и теплоизоляции",
          "Покраска, оклейка обоев, плиточные работы",
          "Только натуральные и экологически безопасные материалы",
          "Установка гипсокартонных конструкций, натяжных потолков, окон, дверей, перегородок",
          "Материалы отделки премиум класса",
          "Декоративная отделка любой сложности"
        ],
        "cons": "",
        "consDescription": []
      }
    ]
  },
  "stepsWork": [
    {
      "id": 1,
      "title": "Вы оставляете заявку",
      "description": "Специалист перезвонит вам в течении 15 минут. Вы обсуждаете ваш будущий ремонт, задаете вопросы.",
      "icon": "/stages/stage1.png"
    },
    {
      "id": 2,
      "title": "К вам приезжает инженер-сметчик",
      "description": "В течение 30 минут он производит замер. Через 12 часов вы получаете точную смету с указанием сроков и стоимости работ.",
      "icon": "/stages/stage2.png"
    },
    {
      "id": 3,
      "title": "Мы заключаем договор",
      "description": "В договоре фиксируются стоимость и сроки. За каждый день просрочки прописывается штраф.",
      "icon": "/stages/stage3.png"
    },
    {
      "id": 4,
      "title": "Закупаем материалы",
      "description": "Работаем напрямую с поставщиками. Поэтому предоставляем для вас скидку от 5 до 30%.",
      "icon": "/stages/stage4.png"
    },
    {
      "id": 5,
      "title": "Приступаем к работе",
      "description": "Уже через 48 часов после подписания договора работа на объекте закипит.",
      "icon": "/stages/stage5.png"
    },
    {
      "id": 6,
      "title": "Наводим порядок и чистоту",
      "description": "Квартира отмывается до блеска. Вы сразу можете заезжать в отремонтированную квартиру.",
      "icon": "/stages/stage6.png"
    }
  ],
  "pageMeta": {
    "home": {
      "title": "Premium Interior | Ремонт и дизайн интерьеров в Беларуси",
      "description": "Premium Interior предлагает профессиональный ремонт и дизайн интерьеров в Беларуси. Сделайте ваш дом стильным и комфортным с нами!",
      "canonical": "/"
    },
    "about": {
      "title": "Premium Interior | О компании и наших услугах по ремонту и дизайну интерьеров",
      "description": "Узнайте больше о компании Premium Interior и наших услугах по ремонту и дизайну интерьеров. Высококачественные решения для вашего дома и офиса.",
      "canonical": "/about"
    },
    "contacts": {
      "title": "Premium Interior | Контакты – свяжитесь с нами для консультаций по ремонту и дизайну",
      "description": "Свяжитесь с нами для консультаций по ремонту и дизайну интерьеров в Беларуси. Мы всегда рады помочь вам создать идеальное пространство!",
      "canonical": "/contacts"
    },
    "design": {
      "title": "Premium Interior | Дизайн интерьеров под ключ в Беларуси",
      "description": "Профессиональный дизайн интерьеров в Беларуси. Premium Interior предлагает уникальные проекты для вашего дома или офиса с индивидуальным подходом.",
      "canonical": "/design"
    },
    "repairs": {
      "title": "Premium Interior | Ремонт интерьеров с гарантией качества в Беларуси",
      "description": "Качественный ремонт интерьеров с гарантией. Мы выполняем ремонтные работы любой сложности и создаем стильные и функциональные пространства.",
      "canonical": "/repairs"
    },
    "user-agreement": {
      "title": "Пользовательское соглашение",
      "description": "Пользовательское соглашение | Premium Interior | Ремонт интерьеров с гарантией качества в Беларуси",
      "canonical": "/documents/user-agreement"
    },
    "privacy-policy": {
      "title": "Политика конфиденциальности",
      "description": "Политика конфиденциальности | Premium Interior | Ремонт интерьеров с гарантией качества в Беларуси",
      "canonical": "/documents/privacy-policy"
    },
    "public-offer": {
      "title": "Публичная оферта",
      "description": "Публичная оферта | Premium Interior | Ремонт интерьеров с гарантией качества в Беларуси",
      "canonical": "/documents/public-offer"
    }
  },
  "papers": [
    {
      "id": 1,
      "title": "Пользовательское соглашение",
      "shortTitle": "user-agreement"
    },
    {
      "id": 2,
      "title": "Политика конфиденциальности",
      "shortTitle": "privacy-policy"
    },
    {
      "id": 3,
      "title": "Публичная оферта",
      "shortTitle": "public-offer"
    }
  ],
  "prices": {
    "repairs": [
      {
        "id": "dismantling-works",
        "title": "Демонтажные работы",
        "description": "Работы по разрушению старых конструкций, удалению ненужных материалов. Включает в себя как частичный, так и полный демонтаж зданий, а также подготовку помещения к дальнейшим ремонтным работам.",
        "image": {
          "src": "/categories/dismantling-works.webp",
          "alt": "Изображение демонтажных работ",
          "quality": 100,
          "width": 1440,
          "height": 810
        },
        "priceList": [
          {
            "service": "Демонтаж кирпичных стен до 40 см",
            "unit": "м²",
            "price": "от 32 р.",
            "canonical": "/services/dismantling-works/dismantling-brick-walls"
          },
          {
            "service": "Демонтаж плитки",
            "unit": "м²",
            "price": "от 16 р.",
            "canonical": "/services/dismantling-works/dismantling-tiles"
          },
          {
            "service": "Демонтаж штукатурки",
            "unit": "м²",
            "price": "от 16 р.",
            "canonical": "/services/dismantling-works/plaster-removal"
          },
          {
            "service": "Демонтаж стяжки",
            "unit": "м²",
            "price": "от 16 р.",
            "canonical": "/services/dismantling-works/dismantling-screed"
          },
          {
            "service": "Демонтаж деревянного пола",
            "unit": "м²",
            "price": "от 16 р.",
            "canonical": "/services/dismantling-works/dismantling-wooden-floor"
          },
          {
            "service": "Демонтаж побелки, старой краски",
            "unit": "м²",
            "price": "от 15 р.",
            "canonical": "/services/dismantling-works/removal-whitewash_old-paint"
          },
          {
            "service": "Демонтаж оконных, дверных блоков (без сохранения)",
            "unit": "м²",
            "price": "от 15 р.",
            "canonical": "/services/dismantling-works/dismantling-window-and-door-units-without-preservation"
          },
          {
            "service": "Демонтаж оконных, дверных блоков (с сохранением)",
            "unit": "м²",
            "price": "от 35 р.",
            "canonical": "/services/dismantling-works/dismantling-window-and-door-units-with-preservation"
          },
          {
            "service": "Демонтаж перегородок из ГКЛ",
            "unit": "м²",
            "price": "от 20 р.",
            "canonical": "/services/dismantling-works/dismantling-GKL-partitions"
          },
          {
            "service": "Демонтаж перегородок кирпич",
            "unit": "м²",
            "price": "от 40 р.",
            "canonical": "/services/dismantling-works/dismantling-brick-partitions"
          },
          {
            "service": "Демонтаж перегородок ПГС",
            "unit": "м²",
            "price": "от 20 р.",
            "canonical": "/services/dismantling-works/dismantling-CBC-partitions"
          },
          {
            "service": "Демонтаж перегородок бетон",
            "unit": "м²",
            "price": "от 150 р.",
            "canonical": "/services/dismantling-works/dismantling-concrete-partitions"
          }
        ]
      },
      {
        "id": "construction-works",
        "title": "Общестроительные работы",
        "description": "Работы по строительству зданий и сооружений, включая заливку фундамента, возведение стен, монтаж фасада, кровельные работы, возведение ограждений и т.д.",
        "image": {
          "src": "/categories/construction-works.webp",
          "alt": "Изображение общестроительных работ",
          "quality": 100,
          "width": 1440,
          "height": 810
        },
        "priceList": [
          {
            "service": "Заливка фундамента",
            "unit": "м³",
            "price": "от 175 р.",
            "canonical": "/services/construction-works/foundation-pouring"
          },
          {
            "service": "Возведение кирпичных стен",
            "unit": "м²",
            "price": "от 120 р.",
            "canonical": "/services/construction-works/brick-wall-construction"
          },
          {
            "service": "Возведение стен ПГС",
            "unit": "м²",
            "price": "от 70 р.",
            "canonical": "/services/construction-works/CBC-wall-construction"
          },
          {
            "service": "Монтаж фасада",
            "unit": "м²",
            "price": "от 28 р.",
            "canonical": "/services/construction-works/facade-installation"
          },
          {
            "service": "Устройство кровли",
            "unit": "м²",
            "price": "от 52 р.",
            "canonical": "/services/construction-works/roofing"
          },
          {
            "service": "Возведение ограждений",
            "unit": "м.п.",
            "price": "от 20 р.",
            "canonical": "/services/construction-works/fence-construction"
          }
        ]
      },
      {
        "id": "installation-works",
        "title": "Монтажные работы",
        "description": "Монтаж гипсокартонных конструкций, панелей по каркасу, звукоизоляционных конструкций, оборудования и т.д.",
        "image": {
          "src": "/categories/installation-works.webp",
          "alt": "Изображение монтажных работ",
          "quality": 100,
          "width": 1440,
          "height": 810
        },
        "priceList": [
          {
            "service": "Монтаж гипсокартонных конструкций",
            "unit": "м²",
            "price": "от 25 р.",
            "canonical": "/services/installation-works/gypboard-installation"
          },
          {
            "service": "Установка вентиляции",
            "unit": "шт.",
            "price": "от 50 р.",
            "canonical": "/services/installation-works/ventilation-installation"
          }
        ]
      },
      {
        "id": "finishing-works",
        "title": "Отделочные работы",
        "description": "Работы по отделке помещений, включая штукатурку, шпатлёвку, укладку плитки и другие отделочные материалы.",
        "image": {
          "src": "/categories/finishing-works.webp",
          "alt": "Изображение отделочных работ",
          "quality": 100,
          "width": 1440,
          "height": 810
        },
        "priceList": [
          {
            "service": "Штукатурка стен",
            "unit": "м²",
            "price": "от 32 р.",
            "canonical": "/services/finishing-works/plastering-walls"
          },
          {
            "service": "Шпатлёвка стен",
            "unit": "м²",
            "price": "от 16 р.",
            "canonical": "/services/finishing-works/wall-puttying"
          },
          {
            "service": "Укладка плитки",
            "unit": "м²",
            "price": "от 48 р.",
            "canonical": "/services/finishing-works/tile-laying"
          },
          {
            "service": "Укладка керамогранита",
            "unit": "м²",
            "price": "от 60 р.",
            "canonical": "/services/finishing-works/stoneware-laying"
          },
          {
            "service": "Укладка ламината",
            "unit": "м²",
            "price": "от 20 р.",
            "canonical": "/services/finishing-works/laminate-flooring"
          },
          {
            "service": "Оклейка стен обоями",
            "unit": "м²",
            "price": "от 12 р.",
            "canonical": "/services/finishing-works/wallpapering"
          },
          {
            "service": "Грунтовка основания",
            "unit": "м²",
            "price": "от 4 р.",
            "canonical": "/services/finishing-works/base-priming"
          }
        ]
      },
      {
        "id": "painting-works",
        "title": "Малярные работы",
        "description": "Работы по покраске различных поверхностей, включая стены, потолки, фасады, а так же применение декоративных составов.",
        "image": {
          "src": "/categories/painting-works.webp",
          "alt": "Изображение малярных работ",
          "quality": 100,
          "width": 1440,
          "height": 810
        },
        "priceList": [
          {
            "service": "Покраска стен и потолков",
            "unit": "м²",
            "price": "от 12 р.",
            "canonical": "/services/painting-works/painting-walls-ceilings"
          },
          {
            "service": "Окраска фасадов",
            "unit": "м²",
            "price": "от 10 р.",
            "canonical": "/services/painting-works/facade-painting"
          },
          {
            "service": "Декоративная отделка",
            "unit": "м²",
            "price": "от 35 р.",
            "canonical": "/services/painting-works/decorative-finishing"
          }
        ]
      },
      {
        "id": "plumbing-works",
        "title": "Сантехнические работы",
        "description": "Работы по установке и ремонту сантехнического оборудования: водоснабжение, канализация, отопление.",
        "image": {
          "src": "/categories/plumbing-works.webp",
          "alt": "Изображение сантехнических работ",
          "quality": 100,
          "width": 1440,
          "height": 810
        },
        "priceList": [
          {
            "service": "Монтаж труб (полипропилен, металлопласт, метал)",
            "unit": "м.п.",
            "price": "от 10 р.",
            "canonical": "/services/plumbing-works/water-pipe-installation"
          },
          {
            "service": "Монтаж смесителя",
            "unit": "шт.",
            "price": "от 70 р.",
            "canonical": "/services/plumbing-works/faucet-installation"
          },
          {
            "service": "Монтаж умывальника",
            "unit": "шт.",
            "price": "от 140 р.",
            "canonical": "/services/plumbing-works/mounting-washbasin"
          },
          {
            "service": "Монтаж унитаза",
            "unit": "шт.",
            "price": "от 140 р.",
            "canonical": "/services/plumbing-works/toilet-installation"
          },
          {
            "service": "Установка душевой кабины",
            "unit": "шт.",
            "price": "от 175 р.",
            "canonical": "/services/plumbing-works/shower-cabin-installation"
          },
          {
            "service": "Подвод точки воды или канализации",
            "unit": "шт.",
            "price": "от 50 р.",
            "canonical": "/services/plumbing-works/water-or-sewage-connection"
          },
          {
            "service": "Установка радиаторов",
            "unit": "шт.",
            "price": "от 105 р.",
            "canonical": "/services/plumbing-works/radiator-installation"
          },
          {
            "service": "Замена стояка",
            "unit": "шт.",
            "price": "от 200 р.",
            "canonical": "/services/plumbing-works/riser-replacement"
          },
          {
            "service": "Замена счётчика",
            "unit": "шт.",
            "price": "от 200 р.",
            "canonical": "/services/plumbing-works/meter-replacement"
          }
        ]
      },
      {
        "id": "electrical-works",
        "title": "Электромонтажные работы",
        "description": "Работы по монтажу электрических сетей, щитков, установке розеток, выключателей, осветительных приборов.",
        "image": {
          "src": "/categories/electrical-works.webp",
          "alt": "Изображение электромонтажных работ",
          "quality": 100,
          "width": 1440,
          "height": 810
        },
        "priceList": [
          {
            "service": "Монтаж электропроводки",
            "unit": "м.п.",
            "price": "от 4 р.",
            "canonical": "/services/electrical-works/wiring-installation"
          },
          {
            "service": "Установка розеток",
            "unit": "шт.",
            "price": "от 20 р.",
            "canonical": "/services/electrical-works/socket-installation"
          },
          {
            "service": "Установка подрозетника",
            "unit": "шт.",
            "price": "от 20 р.",
            "canonical": "/services/electrical-works/socket-outlet-installation"
          },
          {
            "service": "Установка щитка",
            "unit": "шт.",
            "price": "от 70 р.",
            "canonical": "/services/electrical-works/panel-installation"
          },
          {
            "service": "Установка автомата",
            "unit": "шт.",
            "price": "от 48 р.",
            "canonical": "/services/electrical-works/dispenser-installation"
          },
          {
            "service": "Штроба под электрокабель",
            "unit": "м.п.",
            "price": "от 12 р.",
            "canonical": "/services/electrical-works/rutting-electrical-cables"
          },
          {
            "service": "Гофрирование кабеля",
            "unit": "м.п.",
            "price": "от 12 р.",
            "canonical": "/services/electrical-works/cable-corrugation"
          },
          {
            "service": "Установка освещения",
            "unit": "шт.",
            "price": "от 1000 р.",
            "canonical": "/services/electrical-works/lighting-installation"
          }
        ]
      },
      {
        "id": "carpentry-works",
        "title": "Столярные работы",
        "description": "Работы по установке деревянных и пластиковых конструкций, дверей, окон, мебели.",
        "image": {
          "src": "/categories/carpentry-works.webp",
          "alt": "Изображение столярных работ",
          "quality": 100,
          "width": 1440,
          "height": 810
        },
        "priceList": [
          {
            "service": "Установка дверей",
            "unit": "шт.",
            "price": "от 160 р.",
            "canonical": "/services/carpentry-works/door-installation"
          },
          {
            "service": "Установка  окон",
            "unit": "шт.",
            "price": "от 160 р.",
            "canonical": "/services/carpentry-works/window-installation"
          }
        ]
      }
    ],
    "design": [
      {
        "id": "interior-works",
        "title": "Дизайн интерьера",
        "description": "Проектирование интерьеров, подбор материалов, планировка и оформление помещений.",
        "image": {
          "src": "/categories/interior-works.webp",
          "alt": "Изображение работ дизайна",
          "quality": 100,
          "width": 1440,
          "height": 810
        },
        "priceList": [
          {
            "service": "Разработка дизайна комнаты",
            "unit": "м2",
            "price": "от 5000 р.",
            "canonical": "/design/interior-design/razrabotka-dizayna-komnaty"
          },
          {
            "service": "Подбор отделочных материалов",
            "unit": "м2",
            "price": "от 1000 р.",
            "canonical": "/design/interior-design/podbor-otdelочных-materialov"
          }
        ]
      }
    ]
  },
  "reviews": [
    {
      "id": 1,
      "name": "Иван",
      "city": "Жлобин",
      "text": "Ремонт прошёл без единой задержки, всё получилось идеально. Спасибо!",
      "photoUrl": "/reviews/review_1.jpg"
    },
    {
      "id": 2,
      "name": "Мария",
      "city": "Рогачев",
      "text": "Очень довольна работой компании. Все сделано на высшем уровне.",
      "photoUrl": "/reviews/review_2.jpg"
    },
    {
      "id": 3,
      "name": "Ксения",
      "city": "Жлобин",
      "text": "Ремонт завершён раньше срока и с отличным качеством. Рекомендую!",
      "photoUrl": "/reviews/review_3.jpg"
    },
    {
      "id": 4,
      "name": "Дмитрий",
      "city": "Гомель",
      "text": "Парни удивили как качеством так и подходом к делу. Остался доволен!",
      "photoUrl": "/reviews/review_4.jpg"
    }
  ],
  "relatedServices": [
    {
      "id": "expertise",
      "title": "Строительная экспертиза",
      "description": "Проведем экспертизу состояния вашего жилья и предложим улучшения для повышения его стоимости и безопасности.",
      "image": "/services/related/expertise.webp",
      "canonical": "/services/expertise"
    },
    {
      "id": "smart-home",
      "title": "Умный дом и автоматизация",
      "description": "Установим системы умного дома: освещение, климат-контроль, безопасность и управление с телефона.",
      "image": "/services/related/smart-home.webp",
      "canonical": "/services/smart-home"
    },
    {
      "id": "energy-saving",
      "title": "Энергосбережение и экология",
      "description": "Проектируем и устанавливаем решения для энергосбережения, включая солнечные панели, системы отопления и вентиляции с минимальными затратами.",
      "image": "/services/related/energy-saving.webp",
      "canonical": "/services/energy-saving"
    },
    {
      "id": "technical-documentation",
      "title": "Техническая документация",
      "description": "Разработаем детальную документацию по прокладке электросетей, водоснабжения, отопления и освещения.",
      "image": "/services/related/technical-documentation.webp",
      "canonical": "/services/technical-documentation"
    },
    {
      "id": "materials",
      "title": "Подбор и заказ материалов",
      "description": "Подберем и доставим чистовые и черновые материалы для ремонта, а также мебель, сантехнику и освещение.",
      "image": "/services/related/materials.webp",
      "canonical": "/services/materials"
    },
    {
      "id": "cleaning",
      "title": "Вывоз строительного мусора и клининг",
      "description": "Вывезем строительный мусор и сделаем влажную уборку. Вы получите чистую квартиру, готовую к переезду.",
      "image": "/services/related/cleaning.webp",
      "canonical": "/services/cleaning"
    }
  ]
}